timerun/__init__.py
timerun/time.tar
timerun/time_change.py
timerun/jupyter-ai/__init__.py
timerun/jupyter-ai/setup.py
timerun/jupyter-ai/jupyter_ai/__init__.py
timerun/jupyter-ai/jupyter_ai/config_manager.py
timerun/jupyter-ai/jupyter_ai/constants.py
timerun/jupyter-ai/jupyter_ai/extension.py
timerun/jupyter-ai/jupyter_ai/handlers.py
timerun/jupyter-ai/jupyter_ai/history.py
timerun/jupyter-ai/jupyter_ai/models.py
timerun/jupyter-ai/jupyter_ai/callback_handlers/__init__.py
timerun/jupyter-ai/jupyter_ai/callback_handlers/metadata.py
timerun/jupyter-ai/jupyter_ai/chat_handlers/__init__.py
timerun/jupyter-ai/jupyter_ai/chat_handlers/ask.py
timerun/jupyter-ai/jupyter_ai/chat_handlers/base.py
timerun/jupyter-ai/jupyter_ai/chat_handlers/default.py
timerun/jupyter-ai/jupyter_ai/chat_handlers/generate.py
timerun/jupyter-ai/jupyter_ai/chat_handlers/help.py
timerun/jupyter-ai/jupyter_ai/chat_handlers/learn.py
timerun/jupyter-ai/jupyter_ai/completions/__init__.py
timerun/jupyter-ai/jupyter_ai/completions/models.py
timerun/jupyter-ai/jupyter_ai/completions/handlers/__init__.py
timerun/jupyter-ai/jupyter_ai/completions/handlers/base.py
timerun/jupyter-ai/jupyter_ai/completions/handlers/default.py
timerun/jupyter-ai/jupyter_ai/completions/handlers/model_mixin.py
timerun/jupyter-ai/jupyter_ai/context_providers/__init__.py
timerun/jupyter-ai/jupyter_ai/context_providers/base.py
timerun/jupyter-ai/jupyter_ai/context_providers/file.py
timerun/jupyter-ai/jupyter_ai/document_loaders/__init__.py
timerun/jupyter-ai/jupyter_ai/document_loaders/directory.py
timerun/jupyter-ai/jupyter_ai/document_loaders/splitter.py
timerun/jupyter-ai/jupyter_ai/tests/__init__.py
timerun/jupyter-ai/jupyter_ai/tests/test_config_manager.py
timerun/jupyter-ai/jupyter_ai/tests/test_context_providers.py
timerun/jupyter-ai/jupyter_ai/tests/test_directory.py
timerun/jupyter-ai/jupyter_ai/tests/test_extension.py
timerun/jupyter-ai/jupyter_ai/tests/test_handlers.py
time_update-0.5.dist-info/LICENSE
time_update-0.5.dist-info/METADATA
time_update-0.5.dist-info/WHEEL
time_update-0.5.dist-info/top_level.txt
time_update-0.5.dist-info/RECORD
