Metadata-Version: 2.1
Name: time-update
Version: 0.5
Summary: Help to solve the time formate
Home-page: https://github.com/yourusername/your-repo
Author: kongchujun
Author-email: 98514515@qq.com
Classifier: Programming Language :: Python :: 3
Classifier: License :: OSI Approved :: MIT License
Classifier: Operating System :: OS Independent
Requires-Python: >=3.9
License-File: LICENSE
Requires-Dist: requests
